Metadata-Version: 2.1
Name: pyhubitat
Version: 0.0.1
Summary: A python library for interacting with the Hubitat API
Home-page: https://github.com/danielorf/pyhubitat
Author: Daniel Orf
Author-email: danielorf@gmail.com
License: GNU GPLv3
Keywords: hubitat home automation
Platform: UNKNOWN
Classifier: Development Status :: 3 - Alpha
Classifier: Programming Language :: Python :: 3
Classifier: License :: OSI Approved :: GNU General Public License v3 (GPLv3)
Classifier: Operating System :: OS Independent
Requires-Python: >=3.6
